[
  {
    "Full Name": "Alexander ",
    "Email": "info@favourse.com",
    "TipLink": " "
  },
  {
    "Full Name": "Lily Junus",
    "Email": "info@savirtravel.com",
    "TipLink": " "
  },
  {
    "Full Name": "Desi Dwi Jayanti",
    "Email": "infodesidjayanti@gmail.com",
    "TipLink": " "
  },
  {
    "Full Name": "Iqbal Alan Abdullah",
    "Email": "iqbal@royalindo.com",
    "TipLink": " "
  },
  {
    "Full Name": "Iqbal Aristyo",
    "Email": "iqbalaristyo@gmail.com",
    "TipLink": " "
  },
  {
    "Full Name": "Iqbal ",
    "Email": "iqbalsyarib@gmail.com",
    "TipLink": " "
  },
  {
    "Full Name": "Iqri Sulizar",
    "Email": "iqrisulizar@gmail.com",
    "TipLink": " "
  },
  {
    "Full Name": "Ira Alwiyah",
    "Email": "iralwiyah15@gmail.com",
    "TipLink": " "
  },
  {
    "Full Name": "Ira Lathief",
    "Email": "iramerahputih@gmail.com",
    "TipLink": " "
  },
  {
    "Full Name": "Irsan Yanuardi",
    "Email": "irsanyanuardimvn@gmail.com",
    "TipLink": " "
  },
  {
    "Full Name": "Its Freenanda",
    "Email": "itsfreenanda@gmail.com",
    "TipLink": " "
  },
  {
    "Full Name": "Rafhnisyaira Ah",
    "Email": "itsmersah@gmail.com",
    "TipLink": " "
  },
  {
    "Full Name": "Muhammad ",
    "Email": "itsridho.r@gmail.com",
    "TipLink": " "
  },
  {
    "Full Name": "Sondakh Itunes",
    "Email": "itunes.staytunes@gmail.com",
    "TipLink": " "
  },
  {
    "Full Name": "Jamal Shaikh",
    "Email": "jamalshaikh@gmail.com",
    "TipLink": " "
  },
  {
    "Full Name": "Janice Ong",
    "Email": "janicesusanaong@gmail.com",
    "TipLink": " "
  },
  {
    "Full Name": "Jehan Ayu-W",
    "Email": "jehan@kitabisa.com",
    "TipLink": " "
  },
  {
    "Full Name": "Jeremy Tantono",
    "Email": "jeremytantono@yahoo.co.id",
    "TipLink": " "
  },
  {
    "Full Name": "Carbonethics ",
    "Email": "jessica@carbonethics.org",
    "TipLink": " "
  },
  {
    "Full Name": "Jessica Prasetya",
    "Email": "jessica@zeals.asia",
    "TipLink": " "
  },
  {
    "Full Name": "Jessica H",
    "Email": "jessicashu@yahoo.com",
    "TipLink": " "
  },
  {
    "Full Name": "Jevon Setiawan",
    "Email": "jevon@clade.ventures",
    "TipLink": " "
  },
  {
    "Full Name": "Lady Yesisca",
    "Email": "jieladyy@gmail.com",
    "TipLink": " "
  },
  {
    "Full Name": "Joan Margaret",
    "Email": "joan.onbb@yahoo.com",
    "TipLink": " "
  },
  {
    "Full Name": "Joandri Tuessy Mather",
    "Email": "joandri@orugunaizu.com",
    "TipLink": " "
  },
  {
    "Full Name": "Jordan Susantio",
    "Email": "jordansusantio@gmail.com",
    "TipLink": " "
  },
  {
    "Full Name": "Jordha Heryndra",
    "Email": "jordha.heryndra@gmail.com",
    "TipLink": " "
  },
  {
    "Full Name": "Josh Kristianto Education",
    "Email": "joshkristianto.education@gmail.com",
    "TipLink": " "
  },
  {
    "Full Name": "Aliv ",
    "Email": "jovianbintang@gmail.com",
    "TipLink": " "
  },
  {
    "Full Name": "Joy Nathanael",
    "Email": "joynathanael@gmail.com",
    "TipLink": " "
  },
  {
    "Full Name": "Julian Panggih",
    "Email": "julianpanggih04@gmail.com",
    "TipLink": " "
  }
]