[
  {
    "Full Name": "Euro Linus",
    "Email": "eurolinus8@gmail.com",
    "TipLink": " "
  },
  {
    "Full Name": "Evlin Marcelline",
    "Email": "evlin.marcelline@gmail.com",
    "TipLink": " "
  },
  {
    "Full Name": "Rully Ezza",
    "Email": "ezzarully@gmail.com",
    "TipLink": "https://tiplink.io/i#TfeCWBZNim6To31v"
  },
  {
    "Full Name": "Farah Di",
    "Email": "f.fuadi2507@gmail.com",
    "TipLink": " "
  },
  {
    "Full Name": "Fadillah Juliantara",
    "Email": "fadillahjulian@gmail.com",
    "TipLink": " "
  },
  {
    "Full Name": "Fafa Sharief",
    "Email": "fafa.sharief@gmail.com",
    "TipLink": " "
  },
  {
    "Full Name": "Fahmi Tarumanegara",
    "Email": "fahmi.tarumanegara@gmail.com",
    "TipLink": "https://tiplink.io/i#2UVAzASac623PvmNK"
  },
  {
    "Full Name": "Fahmi Saar",
    "Email": "fahmisaar1993@gmail.com",
    "TipLink": " "
  },
  {
    "Full Name": "M. ",
    "Email": "faiqhimam209@gmail.com",
    "TipLink": " "
  },
  {
    "Full Name": "M. ",
    "Email": "faiqhimam209@gmail.com",
    "TipLink": " "
  },
  {
    "Full Name": "Fatya Faizanur",
    "Email": "faizanur.fatya@gmail.com",
    "TipLink": " "
  },
  {
    "Full Name": "Faiz Daffa",
    "Email": "faizdaffa@gmail.com",
    "TipLink": " "
  },
  {
    "Full Name": "Farah ",
    "Email": "farah.dini@dompetaman.com",
    "TipLink": "https://tiplink.io/i#5JoSNX73Bn2tBqjmX"
  },
  {
    "Full Name": "Bilal Faranov",
    "Email": "faranovbilal@gmail.com",
    "TipLink": "https://tiplink.io/i#2fYDDskqxLDmcSNn4"
  },
  {
    "Full Name": "Fariedz Julio",
    "Email": "faridz.julio@gmail.com",
    "TipLink": " "
  },
  {
    "Full Name": "Pandu Mahardika",
    "Email": "farmaninabeauty@gmail.com",
    "TipLink": " "
  },
  {
    "Full Name": "Fathira Ismail",
    "Email": "fathira.fnh@gmail.com",
    "TipLink": "https://tiplink.io/i#4bkoGhAhYQFhXy7ib"
  },
  {
    "Full Name": "Fauzan Al-Rasyid",
    "Email": "fauzan.alrasyid@gmail.com",
    "TipLink": "https://tiplink.io/i#2MyXD8vabu1y5ViC9"
  },
  {
    "Full Name": "Ferdian Supriyanto",
    "Email": "ferdian.work@gmail.com",
    "TipLink": " "
  },
  {
    "Full Name": "Fernanda Ciandra",
    "Email": "fernandaciandra@gmail.com",
    "TipLink": "https://tiplink.io/i#KbAdKYrJJmVZZRDN"
  },
  {
    "Full Name": "Fielda Erniza",
    "Email": "fieldaerniza@gmail.com",
    "TipLink": " "
  },
  {
    "Full Name": "Fikri Fauzan Áöæêãâëµû",
    "Email": "fikrifauzan42@gmail.com",
    "TipLink": " "
  },
  {
    "Full Name": "Filbert Filbert",
    "Email": "filbert1901@gmail.com",
    "TipLink": " "
  },
  {
    "Full Name": "Firman Firman",
    "Email": "firmanyao94@gmail.com",
    "TipLink": "https://tiplink.io/i#255GzaYims2BMdhLj"
  },
  {
    "Full Name": "Dina Carol",
    "Email": "fitri@tnbtcorp.com",
    "TipLink": "https://tiplink.io/i#2Lh72KS5tok4PGVTK"
  },
  {
    "Full Name": "Fiva Ersy Rahmasari",
    "Email": "fiva.ersy@gmail.com",
    "TipLink": "https://tiplink.io/i#3bHHzHDWV6vZbJsMG"
  },
  {
    "Full Name": "Fikra Mahfuzi",
    "Email": "fmkopites@gmail.com",
    "TipLink": " "
  },
  {
    "Full Name": "Fernando Iwantoro",
    "Email": "foiwantoro@gmail.com",
    "TipLink": " "
  },
  {
    "Full Name": "Aulion Wirizqi",
    "Email": "fratella.idea@gmail.com",
    "TipLink": " "
  },
  {
    "Full Name": "Firda ",
    "Email": "frdmwrd2@gmail.com",
    "TipLink": " "
  },
  {
    "Full Name": "Fransisca ",
    "Email": "frhapsari@gmail.com",
    "TipLink": " "
  }
]